{
    "name": "Puzzle",
    "title": "Un sonido fuerte",
    "elements": [
        {
            "type": "Text",
            "text": "Estás en casa viendo televisión solo por la noche. Debes haber estado adormilándote, porque de repente te despiertas después de escuchar un ruido fuerte. Miras afuera y ves un..."
        },
        {
            "type": "WordPuzzle",
            "name": "Un sonido fuerte_Vida Familiar y Doméstica_puzzle1",
            "correct_feedback": "Correcto!",
            "incorrect_feedback": "¡Vaya! Eso no parece correcto. Por favor, espere un momento y intenta de nuevo.",
            "incorrect_delay": 5000,
            "cause_navigation": true,
            "words": [
                "intruso"
            ],
            "missing_letter_count": 1
        }
    ]
}