{
    "name": "Question",
    "title": "Sin planes para el fin de semana",
    "show_buttons": "WhenCorrect",
    "elements": [
        {
            "type": "Text",
            "Text": "¿Tus amingos se han alejado de ti?"
        },
        {
            "type": "Buttons",
            "name": "Sin planes para el fin de semana_Situaciones Sociales_comp_question",
            "correct_feedback": "Correcto!",
            "incorrect_feedback": "¡Vaya! Eso no parece correcto. Por favor, espere un momento y intenta de nuevo.",
            "incorrect_dealy": 5000,
            "buttons": [
                "No",
                "Si"
            ],
            "columnCount": 1,
            "answer": "No"
        }
    ]
}