{
    "name": "Puzzle",
    "title": "Solicitar una subvención",
    "elements": [
        {
            "type": "Text",
            "text": "Quieres iniciar un nuevo proyecto de investigación en tu laboratorio, por lo que solicitas una subvención de financiación. Sin esta financiación, no podrás realizar la investigación que esperas realizar, pero no sabes si tu propuesta es lo suficientemente buena. Crees que no obtendrás la..."
        },
        {
            "type": "Entry",
            "name": "Solicitar una subvención_Salud Mental_entry1"
        }
    ]
}