{
    "name": "Question",
    "title": "Una presentación grande",
    "show_buttons": "WhenCorrect",
    "elements": [
        {
            "type": "Text",
            "Text": "¿Te sientes emocionado por la presentación?"
        },
        {
            "type": "Buttons",
            "name": "Una presentación grande_Académicos/Trabajo/Desarrollo Profesional_comp_question",
            "correct_feedback": "Correcto!",
            "incorrect_feedback": "¡Vaya! Eso no parece correcto. Por favor, espere un momento y intenta de nuevo.",
            "incorrect_dealy": 5000,
            "buttons": [
                "Sí",
                "No"
            ],
            "columnCount": 1,
            "answer": "Si"
        }
    ]
}